{
  "includeSymbols": {
    "HEADER": "// <auto-generated>\r\n//     This code was generated by a tool.\r\n//     Changes to this file may cause incorrect behavior and will be lost if the code is regenerated.\r\n// </auto-generated>",
    "ANT_NETWORK": "AntPlus.LightNetwork",
    "ANT_NETWORK_TEST": "TestNetwork.TestLightNetwork",

    "LIGHT_PANEL_MARGIN": "2",
    "LIGHT_PANEL_FOOTER_HEIGHT": "20",
    "LIGHT_PANEL_BATTERY_OFFSET_Y": "1",

    "H_BATTERY_HEIGHT": "17",
    "H_BATTERY_WIDTH": "49",

    "V_BATTERY_L_WIDTH": "20",

    "H_LIGHT_FONT_OFFSET_X": "4",
    "T_LIGHT_FONT_OFFSET_X": "2",
    "LIGHT_FONT_OFFSET_X": "4",
    "LIGHT_HEIGHT": "32",
    "LIGHT_OFFSET_X": "25",

    "H_LIGHT_L_FONT_OFFSET_X": "4",
    "T_LIGHT_L_FONT_OFFSET_X": "4",
    "LIGHT_L_HEIGHT": "50",
    "LIGHT_L_WIDTH": "68",
    "LIGHT_L_V_BATTERY_OFFSET_X": "60",

    "TITLE_OFFSET_X": "22",

    "CTRL_MODE_OFFSET_X": "8",
    "CTRL_MODE_OFFSET_Y": "11",
    "CTRL_MODE_L_OFFSET_X": "10",
    "CTRL_MODE_L_OFFSET_Y": "14"
  },
  "definedSymbols": ["widget", "highMemory"],
  "outFolder": "source-generated",
  "outFileExtension": "$(__TARGET_NAME).mc",
  "targets": [
    {
      "name": "TouchRectangle",
      "files": ["SmartBikeLights/Source/SmartBikeLights/source-preprocess/BikeLightsView.mc"],
      "definedSymbols": ["rectangle", "touchScreen", "mediumResolution"],
      "includeSymbols": {
        "TARGET": ":rectangle :touchScreen :mediumResolution"
      }
    },
    {
      "name": "Rectangle",
      "files": ["SmartBikeLights/Source/SmartBikeLights/source-preprocess/BikeLightsView.mc"],
      "definedSymbols": ["rectangle", "nonTouchScreen", "mediumResolution"],
      "includeSymbols": {
        "TARGET": ":rectangle :nonTouchScreen :mediumResolution"
      }
    },
    {
      "name": "Round",
      "files": ["SmartBikeLights/Source/SmartBikeLights/source-preprocess/BikeLightsView.mc"],
      "definedSymbols": ["round", "nonTouchScreen", "mediumResolution"],
      "includeSymbols": {
        "TARGET": ":round :nonTouchScreen :mediumResolution"
      }
    },
    {
      "name": "RoundHighResolution",
      "files": ["SmartBikeLights/Source/SmartBikeLights/source-preprocess/BikeLightsView.mc"],
      "definedSymbols": ["round", "nonTouchScreen", "highResolution"],
      "includeSymbols": {
        "TARGET": ":round :nonTouchScreen :highResolution",

        "LIGHT_OFFSET_X": "36",
        "TITLE_OFFSET_X": "32",
        "CTRL_MODE_OFFSET_X": "10",
        "CTRL_MODE_OFFSET_Y": "14",
        "H_BATTERY_WIDTH": "68"
      }
    },
    {
      "name": "Settings",
      "files": ["SmartBikeLights/Source/SmartBikeLights/source-preprocess/AppSettings.mc"],
      "definedSymbols": ["settings"],
      "includeSymbols": {
        "TARGET": ":settings",
        "UIMODULE": "WatchUi."
      }
    },
    {
      "name": "HighResolution",
      "files": [
        "source-preprocess/BikeLightsGlanceView.mc",
        "source-preprocess/BikeLightsControlView.mc"
      ],
      "definedSymbols": ["highResolution"],
      "includeSymbols": {
        "TARGET": ":highResolution"
      }
    },
    {
      "name": "MediumResolution",
      "files": [
        "source-preprocess/BikeLightsGlanceView.mc",
        "source-preprocess/BikeLightsControlView.mc"
      ],
      "definedSymbols": ["mediumResolution"],
      "includeSymbols": {
        "TARGET": ":mediumResolution"
      }
    },
    {
      "name": "LightNetwork",
      "files": [
        "SmartBikeLights/Source/SmartBikeLights/source-preprocess/TestLightNetwork.mc"
      ]
    }
  ]
}